exo_k/__init__.py
exo_k/__version__.py
exo_k/adatabase.py
exo_k/aerosol/__init__.py
exo_k/aerosol/util_aerosol.py
exo_k/aerosols.py
exo_k/atable.py
exo_k/atm.py
exo_k/atm_2band.py
exo_k/atm_evolution/__init__.py
exo_k/atm_evolution/atm_evol.py
exo_k/atm_evolution/condensation.py
exo_k/atm_evolution/condensation_gcm.py
exo_k/atm_evolution/convection.py
exo_k/atm_evolution/settings.py
exo_k/atm_evolution/tracers.py
exo_k/atm_profile.py
exo_k/chemistry.py
exo_k/cia_table.py
exo_k/ciadatabase.py
exo_k/data_table.py
exo_k/fit.py
exo_k/gas_mix.py
exo_k/hires_spectrum.py
exo_k/kdatabase.py
exo_k/ktable.py
exo_k/ktable5d.py
exo_k/ktable_io.py
exo_k/rayleigh.py
exo_k/settings.py
exo_k/two_stream/__init__.py
exo_k/two_stream/two_stream_crisp.py
exo_k/two_stream/two_stream_lmdz.py
exo_k/two_stream/two_stream_toon.py
exo_k/util/32_bands_atmo.dat
exo_k/util/__init__.py
exo_k/util/cst.py
exo_k/util/filenames.py
exo_k/util/interp.py
exo_k/util/molar_heat_capacity.py
exo_k/util/molar_mass.py
exo_k/util/radiation.py
exo_k/util/singleton.py
exo_k/util/spectral_object.py
exo_k/util/spectrum.py
exo_k/util/user_func.py
exo_k/xtable.py
exo_k-1.3.0.dist-info/LICENSE
exo_k-1.3.0.dist-info/METADATA
exo_k-1.3.0.dist-info/WHEEL
exo_k-1.3.0.dist-info/RECORD
