Metadata-Version: 2.1
Name: Exo_k
Version: 1.3.0
Summary: Library to handle radiative opacities from various sources for atmospheric applications
Home-page: https://forge.oasu.u-bordeaux.fr/jleconte/exo_k-public
License: GPLv3
Keywords: opacities,cross sections,correlated-k,spectra,atmosphere,atmospheric,exoplanet,radiative transfer
Author: Jeremy Leconte
Author-email: jeremy.leconte@u-bordeaux.fr
Requires-Python: >=3.8,<4.0
Classifier: Development Status :: 5 - Production/Stable
Classifier: Environment :: Console
Classifier: Framework :: Jupyter
Classifier: Intended Audience :: Developers
Classifier: Intended Audience :: Education
Classifier: Intended Audience :: Science/Research
Classifier: License :: OSI Approved :: GNU General Public License v3 (GPLv3)
Classifier: License :: Other/Proprietary License
Classifier: Operating System :: MacOS
Classifier: Operating System :: OS Independent
Classifier: Operating System :: POSIX
Classifier: Operating System :: POSIX :: Linux
Classifier: Operating System :: Unix
Classifier: Programming Language :: Python :: 3
Classifier: Programming Language :: Python :: 3.8
Classifier: Programming Language :: Python :: 3.9
Classifier: Programming Language :: Python :: 3.10
Classifier: Programming Language :: Python :: 3.11
Classifier: Programming Language :: Python :: 3.12
Classifier: Topic :: Scientific/Engineering
Classifier: Topic :: Scientific/Engineering :: Astronomy
Classifier: Topic :: Scientific/Engineering :: Atmospheric Science
Classifier: Topic :: Scientific/Engineering :: Physics
Classifier: Topic :: Software Development :: Libraries
Requires-Dist: astropy (>=5.1,<6.0) ; python_version == "3.8"
Requires-Dist: astropy (>=6.0,<7.0) ; python_version == "3.9"
Requires-Dist: astropy (>=6.1.1,<7.0.0) ; python_version >= "3.10" and python_version < "4.0"
Requires-Dist: h5py (>=3.10.0)
Requires-Dist: matplotlib (>3.7.3) ; python_version >= "3.9" and python_version < "4.0"
Requires-Dist: matplotlib (>=3.7.3) ; python_version == "3.8"
Requires-Dist: nestle (>=0.2.0,<0.3.0)
Requires-Dist: netCDF4 (<=1.6.5)
Requires-Dist: numba (>=0.58) ; python_version >= "3.9" and python_version < "4.0"
Requires-Dist: numba (>=0.58,<0.59) ; python_version == "3.8"
Requires-Dist: numpy (>=1.23,<1.25) ; python_version == "3.8"
Requires-Dist: numpy (>=1.23,<2.0) ; python_version == "3.9"
Requires-Dist: numpy (>=1.23,<2.0) ; python_version >= "3.10" and python_version < "4.0"
Requires-Dist: pandas (>=2.0) ; python_version == "3.8"
Requires-Dist: pandas (>=2.0,<3.0) ; python_version >= "3.9" and python_version < "4.0"
Requires-Dist: scipy (>=1.10,<2.0) ; python_version == "3.8"
Requires-Dist: scipy (>=1.10,<2.0) ; python_version == "3.9"
Requires-Dist: scipy (>=1.14,<2.0) ; python_version >= "3.10" and python_version < "4.0"
Requires-Dist: typing-extensions (>=4.12.2,<5.0.0)
Project-URL: Documentation, https://perso.astrophy.u-bordeaux.fr/~jleconte/exo_k-doc/index.html
Project-URL: Repository, https://forge.oasu.u-bordeaux.fr/jleconte/exo_k-public
